rapidrush/__init__.py
rapidrush/core.py
rapidrush/__pycache__/__init__.cpython-36.pyc
rapidrush/project/.gitignore
rapidrush/project/MANIFEST.in
rapidrush/project/Makefile
rapidrush/project/setup.py
rapidrush/project/project/__init__.py
rapidrush/project/project/utils/__init__.py
rapidrush/project/project/utils/version.py
rapidrush/project/tests/__init__.py
rapidrush/project/tests/test_version.py
rapidrush/utils/version.py
rapidrush/utils/__pycache__/version.cpython-36.pyc
tests/__init__.py
tests/test_core.py
tests/test_version.py
rapidrush-1.1.0.dist-info/METADATA
rapidrush-1.1.0.dist-info/WHEEL
rapidrush-1.1.0.dist-info/entry_points.txt
rapidrush-1.1.0.dist-info/top_level.txt
rapidrush-1.1.0.dist-info/RECORD
